<?xml version="1.0" encoding="gb2312"?>
<OperationList>
	<InfoModuleTypeProviderId>1</InfoModuleTypeProviderId>
	<InfoModuleTypeId>1</InfoModuleTypeId>
	<InfoModuleProviderId>1</InfoModuleProviderId>
	<InfoServiceProviderId>1</InfoServiceProviderId>
	<NameBaseId>1</NameBaseId>
	<FunctionSection>
		<OperationID>1</OperationID>
		<InfomationElementTableID>3</InfomationElementTableID>
		<InfomationElementID>1</InfomationElementID>
		<OperationType>0</OperationType>
		<ServiceFileName>RegisterTable.dll</ServiceFileName>
		<SupportSystemType>255</SupportSystemType>
		<ModuleType>1</ModuleType>
		<InterfaceFunction>Get_RegisteredOwner</InterfaceFunction>
		<ParameterType>5</ParameterType>
		<IsStorageReturnValueInParameter>1</IsStorageReturnValueInParameter>
		<ParameterValue></ParameterValue>
	</FunctionSection>
	<FunctionSection>
		<OperationID>1</OperationID>
		<InfomationElementTableID>3</InfomationElementTableID>
		<InfomationElementID>2</InfomationElementID>
		<OperationType>0</OperationType>
		<ServiceFileName>RegisterTable.dll</ServiceFileName>
		<SupportSystemType>255</SupportSystemType>
		<ModuleType>1</ModuleType>
		<InterfaceFunction>Get_RegisteredOrganization</InterfaceFunction>
		<ParameterType>5</ParameterType>
		<IsStorageReturnValueInParameter>1</IsStorageReturnValueInParameter>
		<ParameterValue></ParameterValue>
	</FunctionSection>
	<FunctionSection>
		<OperationID>1</OperationID>
		<InfomationElementTableID>3</InfomationElementTableID>
		<InfomationElementID>3</InfomationElementID>
		<OperationType>1</OperationType>
		<ServiceFileName>RegisterTable.dll</ServiceFileName>
		<SupportSystemType>255</SupportSystemType>
		<ModuleType>1</ModuleType>
		<InterfaceFunction>Set_RegisteredOwner</InterfaceFunction>
		<ParameterType>5</ParameterType>
		<IsStorageReturnValueInParameter>0</IsStorageReturnValueInParameter>
		<ParameterValue></ParameterValue>
	</FunctionSection>
	<FunctionSection>
		<OperationID>1</OperationID>
		<InfomationElementTableID>3</InfomationElementTableID>
		<InfomationElementID>4</InfomationElementID>
		<OperationType>1</OperationType>
		<ServiceFileName>RegisterTable.dll</ServiceFileName>
		<SupportSystemType>255</SupportSystemType>
		<ModuleType>1</ModuleType>
		<InterfaceFunction>Set_RegisteredOrganization</InterfaceFunction>
		<ParameterType>5</ParameterType>
		<IsStorageReturnValueInParameter>0</IsStorageReturnValueInParameter>
		<ParameterValue></ParameterValue>
	</FunctionSection>
</OperationList>
